snapify.py
snappify-1.20.dist-info/METADATA
snappify-1.20.dist-info/WHEEL
snappify-1.20.dist-info/entry_points.txt
snappify-1.20.dist-info/top_level.txt
snappify-1.20.dist-info/RECORD
