Metadata-Version: 2.4
Name: snappify
Version: 1.20
Summary: Download Snapchat Story media and optionally monitor for new posts
Home-page: https://github.com/andrilchakraborty/snapify
Author: Cassidy
License: MIT
Requires-Python: >=3.7
Requires-Dist: aiohttp
Requires-Dist: aiofiles
Requires-Dist: beautifulsoup4
Requires-Dist: colorama
Requires-Dist: yarl
